{
    "AppVersion": "1.1.7.0",
    "Title": "Daily Flow",
    "Thumbnail": "lively_thumbnail.jpg",
    "Preview": "preview.gif",
    "Desc": "A wallpaper that doesnt only sit tere and look pretty. It makes you productive. You Can manage your Deadline. To Do List. And get Reminded to do something if thhe deadline upon you.",
    "Author": "Anirban B. (Spider)",
    "License": "MIT",
    "Contact": "https://github.com/AnirbanBiswasGamer/daily-flow",
    "Type": 1,
    "FileName": "index.html",
    "Arguments": "--system-information",
    "IsAbsolutePath": false
}